django_svcs/__init__.py
django_svcs/apps.py
django_svcs/middleware.py
django_svcs/plugin.py
django_svcs/py.typed
django_svcs-0.3.4.dist-info/METADATA
django_svcs-0.3.4.dist-info/WHEEL
django_svcs-0.3.4.dist-info/entry_points.txt
django_svcs-0.3.4.dist-info/licenses/AUTHORS.md
django_svcs-0.3.4.dist-info/licenses/LICENSE
django_svcs-0.3.4.dist-info/RECORD
