Metadata-Version: 2.3
Name: django_svcs
Version: 0.3.4
Summary: A Django integration for SVCS
Project-URL: bugs, https://github.com/offbyone/django_svcs/issues
Project-URL: changelog, https://github.com/django-svcs/django-svcs/blob/main/CHANGELOG.md
Project-URL: homepage, https://github.com/django-svcs/django-svcs
Project-URL: issues, https://github.com/django-svcs/django-svcs/issues
Project-URL: CI, https://github.com/django-svcs/django-svcs/actions
Author-email: Chris Rose <offline@offby1.net>
Maintainer-email: Chris Rose <offline@offby1.net>
License: BSD license
Classifier: Development Status :: 3 - Alpha
Classifier: License :: OSI Approved :: MIT License
Classifier: Programming Language :: Python :: 3.12
Classifier: Programming Language :: Python :: 3.13
Classifier: Typing :: Typed
Requires-Python: >=3.12
Requires-Dist: djp<1.0,>=0.0
Requires-Dist: svcs
